<?xml version="1.0" encoding="utf-8"?>
<ContentType name="BlogUser" parentType="ListItem">
  <DisplayName>Blog</DisplayName>
  <Description>Blog is a leaf content type</Description>
  <Icon>Blog</Icon>
  <Fields>
    <Field name='content_type' type='Element_Textbox'>
      <DisplayName>Display Name</DisplayName>
      <Description>your login name</Description>
    </Field>
    <Field name='content_type_name' type='Element_Textbox'>
      <DisplayName>Machine name</DisplayName>
      <Description>Your real name. Will not be shown to others.</Description>
    </Field>
    <Field name='Role' type='Element_Select'>
      <DisplayName>Access Roles</DisplayName>
      <Description>Select one</Description>
      <Configuration>
        <AllowMultiple>true</AllowMultiple>
        <AllowExtraValue>true</AllowExtraValue>
        <Options>
          <Option selected='true'>administrator</Option>
          <Option>manager</Option>
          <Option>authorized user</Option>
          <Option>new user</Option>
        </Options>
      </Configuration>
    </Field>  
  </Fields>
</ContentType>
